<annotation>
	<folder>train</folder>
	<filename>110.jpeg</filename>
	<path>/home/ubuntu18/ProjectFolder/images/train/110.jpeg</path>
	<source>
		<database>Unknown</database>
	</source>
	<size>
		<width>183</width>
		<height>275</height>
		<depth>3</depth>
	</size>
	<segmented>0</segmented>
	<object>
		<name>mask</name>
		<pose>Unspecified</pose>
		<truncated>0</truncated>
		<difficult>0</difficult>
		<bndbox>
			<xmin>86</xmin>
			<ymin>35</ymin>
			<xmax>108</xmax>
			<ymax>48</ymax>
		</bndbox>
	</object>
</annotation>
